scp_preprocessor/__init__.py
scp_preprocessor/application_error.py
scp_preprocessor/logger.py
scp_preprocessor/main.py
scp_preprocessor/transformations.py
scp_preprocessor/validation.py
scp_preprocessor/version.py
scp_preprocessor/core/__init__.py
scp_preprocessor/core/bin_packer.py
scp_preprocessor/core/remove_elements.py
scp_preprocessor/core/statement_merger.py
scp_preprocessor/core/actions/__init__.py
scp_preprocessor/core/actions/globber.py
scp_preprocessor/core/actions/transformer.py
scp_preprocessor/core/actions/utils.py
service_control_policy_preprocessor-0.0.2.dist-info/licenses/LICENSE
service_control_policy_preprocessor-0.0.2.dist-info/METADATA
service_control_policy_preprocessor-0.0.2.dist-info/WHEEL
service_control_policy_preprocessor-0.0.2.dist-info/entry_points.txt
service_control_policy_preprocessor-0.0.2.dist-info/top_level.txt
service_control_policy_preprocessor-0.0.2.dist-info/RECORD
