Metadata-Version: 2.4
Name: service-control-policy-preprocessor
Version: 0.0.2
Summary: Preprocesses SCPs.
Home-page: https://github.com/aws-samples/service-control-policy-preprocessor
Author: matluttr
Author-email: matluttr@amazon.com
License: MIT-0
Keywords: scp-preprocess aws iam SCP service control policy
Classifier: Intended Audience :: Developers
Classifier: License :: OSI Approved :: MIT License
Classifier: Natural Language :: English
Classifier: Programming Language :: Python :: 3.6
Classifier: Programming Language :: Python :: 3.7
Classifier: Programming Language :: Python :: 3.8
Classifier: Programming Language :: Python :: 3.9
Requires-Python: >=3.6
License-File: LICENSE
Requires-Dist: requests>=2.32
Dynamic: author
Dynamic: author-email
Dynamic: classifier
Dynamic: description
Dynamic: description-content-type
Dynamic: home-page
Dynamic: keywords
Dynamic: license
Dynamic: license-file
Dynamic: requires-dist
Dynamic: requires-python
Dynamic: summary
